[
    {
        "id": 1,
        "src": "https://wallpaperaccess.com/full/1164874.jpg",
        "title": "Good Place",
        "description": "Anim anim adipisicing ipsum anim consequat voluptate est qui velit eu in irure."
    },
    {
        "id": 2,
        "src": "https://adasoft.es/wp-content/uploads/2016/05/HD-Office-Wallpapers-e1463736152125.jpg",
        "title": "Valhala",
        "description": "Anim anim adipisicing ipsum anim consequat voluptate est qui velit eu in irure."
    },
    {
        "id": 3,
        "src": "https://wallpaperset.com/w/full/4/4/6/517256.jpg",
        "title": "Minas Thiryth",
        "description": "Anim anim adipisicing ipsum anim consequat voluptate est qui velit eu in irure."
    },
    {
        "id": 4,
        "src": "https://encrypted-tbn0.gstatic.com/images?q=tbn%3AANd9GcStWaDDWywh7PWlalJf9up3r31eY1LCH3j0XtiewIT2Z50xP_mY&usqp=CAU",
        "title": "Hell",
        "description": "Anim anim adipisicing ipsum anim consequat voluptate est qui velit eu in irure."
    },
    {
        "id": 5,
        "src": "https://encrypted-tbn0.gstatic.com/images?q=tbn%3AANd9GcRGPoXp2BlO9Z49sT7e2DnwJ0yvCoDAmondeIZ5QcqHzuFROzNl&usqp=CAU",
        "title": "Olympous",
        "description": "Anim anim adipisicing ipsum anim consequat voluptate est qui velit eu in irure."
    },
    {
        "id": 6,
        "src": "https://wallpaperaccess.com/full/1164874.jpg",
        "title": "Good Place",
        "description": "Anim anim adipisicing ipsum anim consequat voluptate est qui velit eu in irure."
    },
    {
        "id": 7,
        "src": "https://adasoft.es/wp-content/uploads/2016/05/HD-Office-Wallpapers-e1463736152125.jpg",
        "title": "Valhala",
        "description": "Anim anim adipisicing ipsum anim consequat voluptate est qui velit eu in irure."
    },
    {
        "id": 8,
        "src": "https://wallpaperset.com/w/full/4/4/6/517256.jpg",
        "title": "Minas Thiryth",
        "description": "Anim anim adipisicing ipsum anim consequat voluptate est qui velit eu in irure."
    },
    {
        "id": 9,
        "src": "https://encrypted-tbn0.gstatic.com/images?q=tbn%3AANd9GcStWaDDWywh7PWlalJf9up3r31eY1LCH3j0XtiewIT2Z50xP_mY&usqp=CAU",
        "title": "Hell",
        "description": "Anim anim adipisicing ipsum anim consequat voluptate est qui velit eu in irure."
    },
    {
        "id": 10,
        "src": "https://encrypted-tbn0.gstatic.com/images?q=tbn%3AANd9GcRGPoXp2BlO9Z49sT7e2DnwJ0yvCoDAmondeIZ5QcqHzuFROzNl&usqp=CAU",
        "title": "Olympous",
        "description": "Anim anim adipisicing ipsum anim consequat voluptate est qui velit eu in irure."
    }
]

